tensorop/__init__.py
tensorop/clr.py
tensorop/cross_entropy.py
tensorop/dataloader.py
tensorop/dataset.py
tensorop/datasets.py
tensorop/ensembling.py
tensorop/fit_from_arr.py
tensorop/layers.py
tensorop/loss.py
tensorop/metrics.py
tensorop/misc.py
tensorop/model.py
tensorop/norm.py
tensorop/np_utils.py
tensorop/reg.py
tensorop/torch.py
tensorop/torch_utils.py
tensorop/train.py
tensorop/trainer.py
tensorop/transforms.py
tensorop/triplet_loss.py
tensorop/utils.py
tensorop-0.0.8.1.dist-info/DESCRIPTION.rst
tensorop-0.0.8.1.dist-info/METADATA
tensorop-0.0.8.1.dist-info/RECORD
tensorop-0.0.8.1.dist-info/WHEEL
tensorop-0.0.8.1.dist-info/metadata.json
tensorop-0.0.8.1.dist-info/top_level.txt
