Metadata-Version: 2.0
Name: tensorop
Version: 0.0.8.1
Summary: Simplified DL lib for simplified accelerated research
Home-page: https://github.com/prajjwal1/tensorop
Author: Prajjwal Bhargava
Author-email: prajjwalin@pm.me
License: MIT
Platform: UNKNOWN
Classifier: License :: OSI Approved :: MIT License
Classifier: Programming Language :: Python :: 3.6
Classifier: Programming Language :: Python :: 3.7
Classifier: Topic :: Scientific/Engineering
Classifier: Development Status :: 4 - Beta
Requires-Dist: numpy
